intentional/__about__.py
intentional/__init__.py
intentional/cli.py
intentional/draw.py
intentional/sample_tools.py
intentional-0.0.1.post1.dist-info/METADATA
intentional-0.0.1.post1.dist-info/WHEEL
intentional-0.0.1.post1.dist-info/entry_points.txt
intentional-0.0.1.post1.dist-info/licenses/LICENSE.txt
intentional-0.0.1.post1.dist-info/RECORD
